{
  "contributors": [
    {
      "name": "Cieslak, Matthew",
      "affiliation": "Department of Neuropsychiatry, University of Pennsylvania",
      "orcid": "0000-0002-1931-4734"
    },
    {
      "name": "Camacho, Paul B.",
      "affiliation": "Beckman Institute for Advanced Science & Technology, University of Illinois at Urbana-Champaign, IL, USA",
      "orcid": "0000-0001-9048-7307"
    },
    {
      "name": "Covitz, Sydney",
      "affiliation": "Perelman School of Medicine, University of Pennsylvania, PA, USA",
      "orcid": "0000-0002-7430-4125"
    },
    {
      "name": "Foran, William",
      "affiliation": "Department of Psychiatry, University of Pittsburgh Medical Center",
      "orcid": "0000-0001-7491-9798"
    },
    {
      "name": "He, Xiaosong",
      "affiliation": "Department of Bioengineering, University of Pennsylvania",
      "orcid": "0000-0002-7941-2918"
    },
    {
      "name": "Humphries, Joseph",
      "affiliation": "Turing Medical",
      "orcid": "0000-0002-10257956"
    },
    {
      "name": "Legarreta Gorroño, Jon Haitz",
      "affiliation": "Brigham and Women's Hospital, Mass General Brigham/Harvard Medical School",
      "orcid": "0000-0002-9661-1396"
    },
    {
      "name": "Magnussen, Fredrik",
      "affiliation": "Department of Psychology, University of Oslo",
      "orcid": "0000-0003-2574-1705"
    },
    {
      "name": "Meisler, Steven Lee",
      "affiliation": "Harvard-MIT Program in Speech and Hearing Bioscience and Technology",
      "orcid": "0000-0002-8888-1572"
    },
    {
      "name": "Krause, Michael",
      "affiliation": "Max Planck Institute for Human Development, Berlin, Germany",
      "orcid": "0000-0002-3878-6542"
    },
    {
      "name": "Sadil, Patrick",
      "affiliation": "Johns Hopkins Bloomberg School of Public Health",
      "orcid": "0000-0003-4141-1343"
    },
    {
      "name": "Sydnor, Valerie Jill",
      "affiliation": "Perelman School of Medicine, University of Pennsylvania",
      "orcid": "0000-0002-8640-668X"
    },
    {
      "name": "Satterthwaite, Theodore D.",
      "affiliation": "Perelman School of Medicine, University of Pennsylvania, PA, USA",
      "orcid": "0000-0001-7072-9399"
    }
  ],
  "keywords": [
    "neuroimaging",
    "workflow",
    "pipeline",
    "preprocessing",
    "dMRI",
    "BIDS"
  ],
  "title": "QSIPrep: An integrative platform for preprocessing and reconstructing diffusion MRI",
  "license": "BSD-3-Clause",
  "upload_type": "software"
}